frameioclient/__init__.py
frameioclient/client.py
frameioclient/upload.py
frameioclient/utils.py
frameioclient-0.6.0.dist-info/LICENSE
frameioclient-0.6.0.dist-info/METADATA
frameioclient-0.6.0.dist-info/WHEEL
frameioclient-0.6.0.dist-info/top_level.txt
frameioclient-0.6.0.dist-info/RECORD
