Metadata-Version: 2.1
Name: frameioclient
Version: 0.6.0
Summary: Client library for the Frame.io API
Home-page: https://github.com/frameio/python-frameio-client
Author: Frame.io, Inc.
Author-email: platform@frame.io
License: MIT
Platform: UNKNOWN
